adder/full_adder.vhd
library IEEE;
use IEEE.std_logic_1164.all;

entity full_adder is
   port(a     : in  std_logic;
        b     : in  std_logic;
        c_in  : in  std_logic;
        s     : out std_logic;
        c_out : out std_logic);
end full_adder;

architecture behavioral of full_adder is
begin
  s <= a xor b xor c_in;
  c_out <= (a and b) or (a and c_in) or (b and c_in);
end behavioral;

adder/adder_n.vhd
library IEEE;
use IEEE.std_logic_1164.all;
--use IEEE.numeric_std.all;

entity adder_n is
  generic(N     : integer range 2 to 16 := 8);
     port(a     : in  std_logic_vector(N-1 downto 0);
          b     : in  std_logic_vector(N-1 downto 0);
          c_in  : in  std_logic;
          c_out : out std_logic;
          s     : out std_logic_vector(N-1 downto 0));
end adder_n;

architecture structural of adder_n is
  signal s_carry_in  : std_logic_vector(N-1 downto 0);
  signal s_carry_out : std_logic_vector(N-1 downto 0);
begin
  s_carry_in(0) <= c_in;
  c_out <= s_carry_out(N-1);
  gen_adder : for i in 0 to (N-1) generate
       adder:   entity work.full_adder(behavioral)
                       port map(a     => a(i),
                                b     => b(i),
                                c_in  => s_carry_in(i),
                                s     => s(i),
                                c_out => s_carry_out(i));
  end generate;
  gen_carry : for i in 1 to (N-1) generate
    s_carry_in(i) <= s_carry_out(i-1);
  end generate;
end structural;

triple_port_ram/triple_port_ram.vhd
library IEEE;
use     IEEE.std_logic_1164.all;
use     IEEE.numeric_std.all;

entity triple_port_ram is
  generic
  (
    ADDR_BITS : integer range 2 to 16;
    DATA_BITS : integer range 1 to 32
  );
  port
  (
    clock          : in std_logic;
    -- write port
    write_addr     : in  std_logic_vector(ADDR_BITS-1 downto 0);
    write_data     : in  std_logic_vector(DATA_BITS-1 downto 0);
    write_en       : in  std_logic;
    -- read port
    read_addr      : in  std_logic_vector(ADDR_BITS-1 downto 0);
    read_data      : out std_logic_vector(DATA_BITS-1 downto 0);
    -- auxiliary read port
    aux_read_addr  : in  std_logic_vector(ADDR_BITS-1 downto 0);
    aux_read_data  : out std_logic_vector(DATA_BITS-1 downto 0)
  );
end triple_port_ram;


architecture synchronous_new of triple_port_ram is
  type ram_t is array(0 to 2**ADDR_BITS-1) of std_logic_vector(DATA_BITS-1 downto 0);
  signal ram : ram_t := (others => (others => '0'));
begin
  -- synchronous
  process(clock) is
  begin
    if rising_edge(clock) then
      if write_en = '1' then
        ram(to_integer(unsigned(write_addr))) <= write_data;
      end if;
      if read_addr = write_addr and write_en = '1' then
        read_data <= transport write_data after 50 ps;
      else
        read_data <= transport ram(to_integer(unsigned(read_addr))) after 400 ps;
      end if;

      
      
      
    end if;
  end process;
  process(aux_read_addr,write_addr,write_data) is
  begin
    if aux_read_addr = write_addr and write_en = '1' then
      aux_read_data <= transport write_data after 50 ps;
    else
      aux_read_data <= transport ram(to_integer(unsigned(aux_read_addr))) after 400 ps;
    end if;
  end process;
end synchronous_new;


























-- architecture synchronous_old of triple_port_ram is
--   type ram_t is array(0 to 2**ADDR_BITS-1) of std_logic_vector(DATA_BITS-1 downto 0);
--   signal ram : ram_t := (others => (others => '0'));
-- begin
--   -- synchronous
--   process(clock) is
--   begin
--     if rising_edge(clock) then
--       if write_en = '1' then
--         ram(to_integer(unsigned(write_addr))) <= write_data;
--       end if;
--       -- always read read old data
--       read_data <= transport ram(to_integer(unsigned(read_addr))) after 400 ps;
--     end if;
--   end process;
-- end synchronous_old;



-- architecture asynchronous_old of triple_port_ram is
--   type ram_t is array(0 to 2**ADDR_BITS-1) of std_logic_vector(DATA_BITS-1 downto 0);
--   signal ram : ram_t := (others => (others => '0'));
-- begin
--   -- synchronous
--   process(clock) is
--   begin
--     if rising_edge(clock) and write_en = '1' then
--         ram(to_integer(unsigned(write_addr))) <= write_data;
--     end if;
--   end process;
--   -- asynchronous
--   process(read_addr) is
--   begin
--     read_data <= transport ram(to_integer(unsigned(read_addr))) after 400 ps;
--   end process;
-- end asynchronous_old;

-- architecture asynchronous_new of triple_port_ram is
--   type ram_t is array(0 to 2**ADDR_BITS-1) of std_logic_vector(DATA_BITS-1 downto 0);
--   signal ram : ram_t := (others => (others => '0'));
-- begin
--   -- synchronous
--   process(clock) is
--   begin
--     if rising_edge(clock) and write_en = '1' then
--       ram(to_integer(unsigned(write_addr))) <= write_data;
--     end if;
--   end process;
--   -- asynchronous
--   process(read_addr,write_addr,write_en) is
--   begin
--     if read_addr = write_addr and write_en = '1' then
--       read_data <= transport write_data after 50 ps;
--     else
--       read_data <= transport ram(to_integer(unsigned(read_addr))) after 400 ps;
--     end if;
--   end process;
-- end asynchronous_new;

register/my_register.vhd
library IEEE;
use IEEE.std_logic_1164.all;

entity my_register is
  generic(N : integer range 2 to 8 := 4);
  port(
        clock : in  std_logic;
        d     : in  std_logic_vector(N-1 downto 0);
        q     : out std_logic_vector(N-1 downto 0):=(others => '0')
      );
end my_register;

architecture behavioral of my_register is
begin
  process(clock) is
  begin
    if rising_edge(clock) then
      q <= transport d after 10 ps;
    end if;
  end process;
end behavioral;

accumulator_single_cycle.vhd
library IEEE;
use     IEEE.std_logic_1164.all;
use     IEEE.numeric_std.all;

entity accumulator is
    generic
    (
    ADDR_BITS : integer range 2 to 8 := 4;
    DATA_BITS_LOG2 : integer range 2 to 5 := 3
    );
    port
    (
    clock : in std_logic;
    -- write port
    write_addr : in std_logic_vector(ADDR_BITS-1 downto 0);
    write_inc : in std_logic_vector(2**DATA_BITS_LOG2-1 downto 0);
    -- read port
    read_addr : in std_logic_vector(ADDR_BITS-1 downto 0);
    read_data : out std_logic_vector(2**DATA_BITS_LOG2-1 downto 0)
    );
end accumulator;


architecture structural of accumulator is
  signal s_write_addr_stable : std_logic_vector(ADDR_BITS-1 downto 0);
  signal s_write_inc_stable,s_value_to_write, s_aux_r_d:  std_logic_vector(2**DATA_BITS_LOG2-1 downto 0);
begin
    my_register_addr: entity work.my_register(behavioral)
                 generic map(N => ADDR_BITS)
                    port map(clock => clock,
                              d     => write_addr,
                              q     => s_write_addr_stable);

    -- my_register_addr2: entity work.my_register(behavioral)
    --                    generic map(N => ADDR_BITS)
    --                       port map(clock => clock,
    --                                d     => s_write_addr_stable,
    --                                q     => delayed_write_addr2);

    my_register_inc:  entity work.my_register(behavioral)
                      generic map(N => 2**DATA_BITS_LOG2)
                         port map(clock => clock,
                                  d     => write_inc,
                                  q     => s_write_inc_stable);



  --     process(clock)
  -- begin
  --   if rising_edge(clock) then
  --     if write_inc_changed = '1' then
  --       -- adder_n executes and s_value_to_write gets updated
  --       s_value_to_write <= s_value_to_write; -- Signal propagation depends on this
  --     else
  --       s_value_to_write <= s_value_to_write; -- Optional: Hold previous value
  --     end if;
  --   end if;
  -- end process;
    triple_port_ram:  entity work.triple_port_ram(synchronous_new)
                      generic map(ADDR_BITS => ADDR_BITS, DATA_BITS_LOG2 => DATA_BITS_LOG2)
                         port map(clock         => clock,
                                  write_en      => '1',
                                  write_addr    => s_write_addr_stable,
                                  write_data    => s_value_to_write,
                                  
                                  read_addr     => read_addr,
                                  read_data     => read_data,
                                  aux_read_addr => s_write_addr_stable,
                                  aux_read_data => s_aux_r_d);


    adder_n:  entity work.adder_n(structural)
    generic map(N => 2**DATA_BITS_LOG2)
        port map(a     => s_aux_r_d,
                b     => s_write_inc_stable,
                c_in  => '0',
                s     => s_value_to_write,
                c_out  => open);
    
    -- process(s_value_to_write) is
    -- begin
    --   if(s_write_inc_stable = write_inc) then
    --     s_value_to_write <= s_aux_r_d;
    --   end if;
    -- end process;
    -- s_write_inc_stable <= (others => '0');

  -- process(s_value_to_write) is
  -- begin
  --   s_value_to_write <= (others => '0');
  -- end process;
end structural;

shift_accumulator_tb.vhd
--
-- AAD 2024/2025, accumulator test bench
--

library IEEE;
use IEEE.std_logic_1164.all;
use IEEE.numeric_std.all;

entity accumulator_tb is
end accumulator_tb;

architecture stimulus of accumulator_tb is
  constant ADDR_BITS      : positive := 4;
  constant DATA_BITS_LOG2 : positive := 3;
  signal clock         : std_logic;
  signal s_write_addr  : std_logic_vector(        ADDR_BITS-1 downto 0);
  signal s_write_inc   : std_logic_vector(2**DATA_BITS_LOG2-1 downto 0);
  -- signal s_write_shift : std_logic_vector(   DATA_BITS_LOG2-1 downto 0);
  signal s_read_addr   : std_logic_vector(        ADDR_BITS-1 downto 0);
  signal s_read_data   : std_logic_vector(2**DATA_BITS_LOG2-1 downto 0);
begin
  uut : entity work.accumulator(structural)
               generic map
               (
                 ADDR_BITS      => ADDR_BITS,
                 DATA_BITS_LOG2 => DATA_BITS_LOG2
               )
               port map
               (
                 clock       => clock,
                 write_addr  => s_write_addr,
                 write_inc   => s_write_inc,
                --  write_shift => s_write_shift,
                 read_addr   => s_read_addr,
                 read_data   => s_read_data
               );
  
  -- clock generation
  clock_stim : process is
  begin
    for cycle in 0 to 10+2+2**ADDR_BITS loop
      clock <= '0';
      wait for 500 ps;
      clock <= '1';
      wait for 500 ps;
    end loop;
  wait;
  end process;
  -- write port (10 clock cycles with activity)
  write_stim : process is
  begin
    -- T=0 --- a[3] = 7
    s_write_addr  <= std_logic_vector(to_unsigned(   3 ,ADDR_BITS));
    s_write_inc   <= std_logic_vector(to_unsigned(   7 ,2**DATA_BITS_LOG2));
    -- s_write_shift <= std_logic_vector(to_unsigned(   0 ,DATA_BITS_LOG2));
    wait for 1000 ps;
    -- T=1 --- a[15] = 48 (final)
    s_write_addr  <= std_logic_vector(to_unsigned(  15 ,ADDR_BITS));
    s_write_inc   <= std_logic_vector(to_unsigned(   3 ,2**DATA_BITS_LOG2));
    -- s_write_shift <= std_logic_vector(to_unsigned(   4 ,DATA_BITS_LOG2));
    wait for 1000 ps;
    -- T=2 --- a[ 3] = 9
    s_write_addr  <= std_logic_vector(to_unsigned(   3 ,ADDR_BITS));
    s_write_inc   <= std_logic_vector(to_unsigned(   1 ,2**DATA_BITS_LOG2));
    -- s_write_shift <= std_logic_vector(to_unsigned(   1 ,DATA_BITS_LOG2));
    wait for 1000 ps;
    -- T=3 --- a[ 3] = 16
    s_write_addr  <= std_logic_vector(to_unsigned(   3 ,ADDR_BITS));
    s_write_inc   <= std_logic_vector(to_unsigned(   7 ,2**DATA_BITS_LOG2));
    -- s_write_shift <= std_logic_vector(to_unsigned(   0 ,DATA_BITS_LOG2));
    wait for 1000 ps;
    -- T=4 --- a[ 5] = 128 (final)
    s_write_addr  <= std_logic_vector(to_unsigned(   5 ,ADDR_BITS));
    s_write_inc   <= std_logic_vector(to_unsigned(  64 ,2**DATA_BITS_LOG2));
    -- s_write_shift <= std_logic_vector(to_unsigned(   1 ,DATA_BITS_LOG2));
    wait for 1000 ps;
    -- T=5 --- a[ 4] = 64
    s_write_addr  <= std_logic_vector(to_unsigned(   4 ,ADDR_BITS));
    s_write_inc   <= std_logic_vector(to_unsigned(   1 ,2**DATA_BITS_LOG2));
    -- s_write_shift <= std_logic_vector(to_unsigned(   6 ,DATA_BITS_LOG2));
    wait for 1000 ps;
    -- T=6 --- a[ 4] = 64 (final)
    s_write_addr  <= std_logic_vector(to_unsigned(   4 ,ADDR_BITS));
    s_write_inc   <= std_logic_vector(to_unsigned(  16 ,2**DATA_BITS_LOG2));
    -- s_write_shift <= std_logic_vector(to_unsigned(   6 ,DATA_BITS_LOG2));
    wait for 1000 ps;
    -- T=7 --- a[ 3] = 32 (final)
    s_write_addr  <= std_logic_vector(to_unsigned(   3 ,ADDR_BITS));
    s_write_inc   <= std_logic_vector(to_unsigned(   1 ,2**DATA_BITS_LOG2));
    -- s_write_shift <= std_logic_vector(to_unsigned(   4 ,DATA_BITS_LOG2));
    wait for 1000 ps;
    -- T=8 --- a[10] = 144 (final)
    s_write_addr  <= std_logic_vector(to_unsigned(  10 ,ADDR_BITS));
    s_write_inc   <= std_logic_vector(to_unsigned( 100 ,2**DATA_BITS_LOG2));
    -- s_write_shift <= std_logic_vector(to_unsigned(   2 ,DATA_BITS_LOG2));
    wait for 1000 ps;
    -- T=9 --- a[ 2] = 34 (final)
    s_write_addr  <= std_logic_vector(to_unsigned(   2 ,ADDR_BITS));
    s_write_inc   <= std_logic_vector(to_unsigned(  17 ,2**DATA_BITS_LOG2));
    -- s_write_shift <= std_logic_vector(to_unsigned(   1 ,DATA_BITS_LOG2));
    wait for 1000 ps;
    -- done
    s_write_addr  <= std_logic_vector(to_unsigned(   0 ,ADDR_BITS));
    s_write_inc   <= std_logic_vector(to_unsigned(   0 ,2**DATA_BITS_LOG2));
    -- s_write_shift <= std_logic_vector(to_unsigned(   0 ,DATA_BITS_LOG2));
    wait;
  end process;
  -- read port (at the end, read the entire memory)
  read_stim : process is
  begin
    s_read_addr <= std_logic_vector(to_unsigned( 3 ,ADDR_BITS));
    wait for (10+2)*1000 ps;
    for_1 : for i in 0 to 2**ADDR_BITS-1 loop
      s_read_addr <= std_logic_vector(to_unsigned(i,ADDR_BITS));
      wait for 1000 ps;
    end loop;
    wait;
  end process;
end stimulus;

accumulator.vcd
$date
  Sat Dec 21 21:10:32 2024
$end
$version
  GHDL v0
$end
$timescale
  1 fs
$end
$scope module standard $end
$upscope $end
$scope module textio $end
$upscope $end
$scope module std_logic_1164 $end
$upscope $end
$scope module numeric_std $end
$upscope $end
$scope module accumulator_tb $end
$var reg 1 ! clock $end
$var reg 4 " s_write_addr[3:0] $end
$var reg 8 # s_write_inc[7:0] $end
$var reg 4 $ s_read_addr[3:0] $end
$var reg 8 % s_read_data[7:0] $end
$scope module uut $end
$var reg 1 & clock $end
$var reg 4 ' write_addr[3:0] $end
$var reg 8 ( write_inc[7:0] $end
$var reg 4 ) read_addr[3:0] $end
$var reg 8 * read_data[7:0] $end
$var reg 4 + s_write_addr_stable[3:0] $end
$var reg 8 , s_write_inc_stable[7:0] $end
$var reg 8 - s_value_to_write[7:0] $end
$var reg 8 . s_aux_r_d[7:0] $end
$scope module my_register_addr $end
$var reg 1 / clock $end
$var reg 4 0 d[3:0] $end
$var reg 4 1 q[3:0] $end
$upscope $end
$scope module my_register_inc $end
$var reg 1 2 clock $end
$var reg 8 3 d[7:0] $end
$var reg 8 4 q[7:0] $end
$upscope $end
$scope module triple_port_ram $end
$var reg 1 5 clock $end
$var reg 4 6 write_addr[3:0] $end
$var reg 8 7 write_data[7:0] $end
$var reg 1 8 write_en $end
$var reg 4 9 read_addr[3:0] $end
$var reg 8 : read_data[7:0] $end
$var reg 4 ; aux_read_addr[3:0] $end
$var reg 8 < aux_read_data[7:0] $end
$comment ram is not handled $end
$upscope $end
$scope module adder_n $end
$var reg 8 = a[7:0] $end
$var reg 8 > b[7:0] $end
$var reg 1 ? c_in $end
$var reg 1 @ c_out $end
$var reg 8 A s[7:0] $end
$var reg 8 B s_carry_in[7:0] $end
$var reg 8 C s_carry_out[7:0] $end
$scope module gen_adder(0) $end
$scope module adder $end
$var reg 1 D a $end
$var reg 1 E b $end
$var reg 1 F c_in $end
$var reg 1 G s $end
$var reg 1 H c_out $end
$upscope $end
$upscope $end
$scope module gen_adder(1) $end
$scope module adder $end
$var reg 1 I a $end
$var reg 1 J b $end
$var reg 1 K c_in $end
$var reg 1 L s $end
$var reg 1 M c_out $end
$upscope $end
$upscope $end
$scope module gen_adder(2) $end
$scope module adder $end
$var reg 1 N a $end
$var reg 1 O b $end
$var reg 1 P c_in $end
$var reg 1 Q s $end
$var reg 1 R c_out $end
$upscope $end
$upscope $end
$scope module gen_adder(3) $end
$scope module adder $end
$var reg 1 S a $end
$var reg 1 T b $end
$var reg 1 U c_in $end
$var reg 1 V s $end
$var reg 1 W c_out $end
$upscope $end
$upscope $end
$scope module gen_adder(4) $end
$scope module adder $end
$var reg 1 X a $end
$var reg 1 Y b $end
$var reg 1 Z c_in $end
$var reg 1 [ s $end
$var reg 1 \ c_out $end
$upscope $end
$upscope $end
$scope module gen_adder(5) $end
$scope module adder $end
$var reg 1 ] a $end
$var reg 1 ^ b $end
$var reg 1 _ c_in $end
$var reg 1 ` s $end
$var reg 1 a c_out $end
$upscope $end
$upscope $end
$scope module gen_adder(6) $end
$scope module adder $end
$var reg 1 b a $end
$var reg 1 c b $end
$var reg 1 d c_in $end
$var reg 1 e s $end
$var reg 1 f c_out $end
$upscope $end
$upscope $end
$scope module gen_adder(7) $end
$scope module adder $end
$var reg 1 g a $end
$var reg 1 h b $end
$var reg 1 i c_in $end
$var reg 1 j s $end
$var reg 1 k c_out $end
$upscope $end
$upscope $end
$scope module gen_carry(1) $end
$upscope $end
$scope module gen_carry(2) $end
$upscope $end
$scope module gen_carry(3) $end
$upscope $end
$scope module gen_carry(4) $end
$upscope $end
$scope module gen_carry(5) $end
$upscope $end
$scope module gen_carry(6) $end
$upscope $end
$scope module gen_carry(7) $end
$upscope $end
$upscope $end
$upscope $end
$upscope $end
$enddefinitions $end
#0
0!
b0011 "
b00000111 #
b0011 $
bUUUUUUUU %
0&
b0011 '
b00000111 (
b0011 )
bUUUUUUUU *
b0000 +
b00000000 ,
b00000000 -
b00000000 .
0/
b0011 0
b0000 1
02
b00000111 3
b00000000 4
05
b0000 6
b00000000 7
18
b0011 9
bUUUUUUUU :
b0000 ;
b00000000 <
b00000000 =
b00000000 >
0?
0@
b00000000 A
b00000000 B
b00000000 C
0D
0E
0F
0G
0H
0I
0J
0K
0L
0M
0N
0O
0P
0Q
0R
0S
0T
0U
0V
0W
0X
0Y
0Z
0[
0\
0]
0^
0_
0`
0a
0b
0c
0d
0e
0f
0g
0h
0i
0j
0k
#500000
1!
1&
1/
12
15
#510000
b0011 +
b00000111 ,
b00000111 -
b0011 1
b00000111 4
b0011 6
b00000111 7
b0011 ;
b00000111 >
b00000111 A
1E
1G
1J
1L
1O
1Q
#550000
b00000000 %
b00000000 *
b00000000 :
#1000000
0!
b1111 "
b00000011 #
0&
b1111 '
b00000011 (
0/
b1111 0
02
b00000011 3
05
#1500000
1!
1&
b00001110 -
b00000111 .
1/
12
15
b00001110 7
b00000111 <
b00000111 =
b00001110 A
b00001110 B
b00000111 C
1D
0G
1H
1I
1K
1L
1M
1N
1P
1Q
1R
1U
1V
#1510000
b1111 +
b00000011 ,
b00000011 -
b00000000 .
b1111 1
b00000011 4
b1111 6
b00000011 7
b1111 ;
b00000000 <
b00000000 =
b00000011 >
b00000011 A
b00000000 B
b00000000 C
0D
1G
0H
0I
0K
1L
0M
0N
0O
0P
0Q
0R
0U
0V
#1550000
b00000111 %
b00000111 *
b00000111 :
#2000000
0!
b0011 "
b00000001 #
0&
b0011 '
b00000001 (
0/
b0011 0
02
b00000001 3
05
#2500000
1!
1&
b00000110 -
b00000011 .
1/
12
15
b00000110 7
b00000011 <
b00000011 =
b00000110 A
b00000110 B
b00000011 C
1D
0G
1H
1I
1K
1L
1M
1P
1Q
#2510000
b0011 +
b00000001 ,
b00001000 -
b00000111 .
b0011 1
b00000001 4
b0011 6
b00001000 7
b0011 ;
b00000111 <
b00000111 =
b00000001 >
b00001000 A
b00001110 B
b00000111 C
0J
0L
1N
0Q
1R
1U
1V
#2550000
b00000111 *
b00000111 :
#3000000
0!
b00000111 #
0&
b00000111 (
0/
02
b00000111 3
05
#3500000
1!
1&
b00001001 -
b00001000 .
1/
12
15
b00001001 7
b00001000 <
b00001000 =
b00001001 A
b00000000 B
b00000000 C
0D
1G
0H
0I
0K
0L
0M
0N
0P
0Q
0R
1S
0U
1V
0W
0Z
0[
#3510000
b00000111 ,
b00001111 -
b0011 1
b00000111 4
b00001111 7
b00000111 >
b00001111 A
1J
1L
1O
1Q
#3550000
b00001000 %
b00001000 *
b00001000 :
#4000000
0!
b0101 "
b01000000 #
0&
b0101 '
b01000000 (
0/
b0101 0
02
b01000000 3
05
#4500000
1!
1&
b00010110 -
b00001111 .
1/
12
15
b00010110 7
b00001111 <
b00001111 =
b00010110 A
b00011110 B
b00001111 C
1D
0G
1H
1I
1K
1L
1M
1N
1P
1Q
1R
1U
0V
1W
1Z
1[
#4510000
b0101 +
b01000000 ,
b01000000 -
b00000000 .
b0101 1
b01000000 4
b0101 6
b01000000 7
b0101 ;
b00000000 <
b00000000 =
b01000000 >
b01000000 A
b00000000 B
b00000000 C
0D
0E
0G
0H
0I
0J
0K
0L
0M
0N
0O
0P
0Q
0R
0S
0U
0V
0W
0Z
0[
1c
1e
#4550000
b00001111 %
b00001111 *
b00001111 :
#5000000
0!
b0100 "
b00000001 #
0&
b0100 '
b00000001 (
0/
b0100 0
02
b00000001 3
05
#5500000
1!
1&
b10000000 -
b01000000 .
1/
12
15
b10000000 7
b01000000 <
b01000000 =
b10000000 A
b10000000 B
b01000000 C
1b
0e
1f
1i
1j
#5510000
b0100 +
b00000001 ,
b00000001 -
b00000000 .
b0100 1
b00000001 4
b0100 6
b00000001 7
b0100 ;
b00000000 <
b00000000 =
b00000001 >
b00000001 A
b00000000 B
b00000000 C
1E
1G
0b
0c
0e
0f
0i
0j
#5550000
b00001111 *
b00001111 :
#6000000
0!
b00010000 #
0&
b00010000 (
0/
02
b00010000 3
05
#6500000
1!
1&
b00000010 -
b00000001 .
1/
12
15
b00000010 7
b00000001 <
b00000001 =
b00000010 A
b00000010 B
b00000001 C
1D
0G
1H
1K
1L
#6510000
b00010000 ,
b00010001 -
b0100 1
b00010000 4
b00010001 7
b00010000 >
b00010001 A
b00000000 B
b00000000 C
0E
1G
0H
0K
0L
1Y
1[
#6550000
b00001111 *
b00001111 :
#7000000
0!
b0011 "
b00000001 #
0&
b0011 '
b00000001 (
0/
b0011 0
02
b00000001 3
05
#7500000
1!
1&
b00100001 -
b00010001 .
1/
12
15
b00100001 7
b00010001 <
b00010001 =
b00100001 A
b00100000 B
b00010000 C
1X
0[
1\
1_
1`
#7510000
b0011 +
b00000001 ,
b00010000 -
b00001111 .
b0011 1
b00000001 4
b0011 6
b00010000 7
b0011 ;
b00001111 <
b00001111 =
b00000001 >
b00010000 A
b00011110 B
b00001111 C
1E
0G
1H
1I
1K
0L
1M
1N
1P
0Q
1R
1S
1U
0V
1W
0X
0Y
1Z
1[
0\
0_
0`
#7550000
b00001111 *
b00001111 :
#8000000
0!
b1010 "
b01100100 #
0&
b1010 '
b01100100 (
0/
b1010 0
02
b01100100 3
05
#8500000
1!
1&
b00010001 -
b00010000 .
1/
12
15
b00010001 7
b00010000 <
b00010000 =
b00010001 A
b00000000 B
b00000000 C
0D
1G
0H
0I
0K
0L
0M
0N
0P
0Q
0R
0S
0U
0V
0W
1X
0Z
1[
0\
0_
0`
#8510000
b1010 +
b01100100 ,
b01100100 -
b00000000 .
b1010 1
b01100100 4
b1010 6
b01100100 7
b1010 ;
b00000000 <
b00000000 =
b01100100 >
b01100100 A
0E
0G
1O
1Q
0X
0[
1^
1`
1c
1e
#8550000
b00010000 %
b00010000 *
b00010000 :
#9000000
0!
b0010 "
b00010001 #
0&
b0010 '
b00010001 (
0/
b0010 0
02
b00010001 3
05
#9500000
1!
1&
b11001000 -
b01100100 .
1/
12
15
b11001000 7
b01100100 <
b01100100 =
b11001000 A
b11001000 B
b01100100 C
1N
0Q
1R
1U
1V
1]
0`
1a
1b
1d
1e
1f
1i
1j
#9510000
b0010 +
b00010001 ,
b00010001 -
b00000000 .
b0010 1
b00010001 4
b0010 6
b00010001 7
b0010 ;
b00000000 <
b00000000 =
b00010001 >
b00010001 A
b00000000 B
b00000000 C
1E
1G
0N
0O
0Q
0R
0U
0V
1Y
1[
0]
0^
0`
0a
0b
0c
0d
0e
0f
0i
0j
#9550000
b00010000 *
b00010000 :
#10000000
0!
b0000 "
b00000000 #
0&
b0000 '
b00000000 (
0/
b0000 0
02
b00000000 3
05
#10500000
1!
1&
b00100010 -
b00010001 .
1/
12
15
b00100010 7
b00010001 <
b00010001 =
b00100010 A
b00100010 B
b00010001 C
1D
0G
1H
1K
1L
1X
0[
1\
1_
1`
#10510000
b0000 +
b00000000 ,
b00000000 -
b00000000 .
b0000 1
b00000000 4
b0000 6
b00000000 7
b0000 ;
b00000000 <
b00000000 =
b00000000 >
b00000000 A
b00000000 B
b00000000 C
0D
0E
0G
0H
0K
0L
0X
0Y
0[
0\
0_
0`
#10550000
b00010000 *
b00010000 :
#11000000
0!
0&
0/
02
05
#11500000
1!
1&
1/
12
15
#11510000
b0000 1
b00000000 4
#11550000
b00010000 *
b00010000 :
#12000000
0!
b0000 $
0&
b0000 )
0/
02
05
b0000 9
#12500000
1!
1&
1/
12
15
#12510000
b0000 1
b00000000 4
#12550000
b00000000 %
b00000000 *
b00000000 :
#13000000
0!
b0001 $
0&
b0001 )
0/
02
05
b0001 9
#13500000
1!
1&
1/
12
15
#13510000
b0000 1
b00000000 4
#13550000
b00000000 *
b00000000 :
#14000000
0!
b0010 $
0&
b0010 )
0/
02
05
b0010 9
#14500000
1!
1&
1/
12
15
#14510000
b0000 1
b00000000 4
#14550000
b00010001 %
b00010001 *
b00010001 :
#15000000
0!
b0011 $
0&
b0011 )
0/
02
05
b0011 9
#15500000
1!
1&
1/
12
15
#15510000
b0000 1
b00000000 4
#15550000
b00010000 %
b00010000 *
b00010000 :
#16000000
0!
b0100 $
0&
b0100 )
0/
02
05
b0100 9
#16500000
1!
1&
1/
12
15
#16510000
b0000 1
b00000000 4
#16550000
b00010001 %
b00010001 *
b00010001 :
#17000000
0!
b0101 $
0&
b0101 )
0/
02
05
b0101 9
#17500000
1!
1&
1/
12
15
#17510000
b0000 1
b00000000 4
#17550000
b01000000 %
b01000000 *
b01000000 :
#18000000
0!
b0110 $
0&
b0110 )
0/
02
05
b0110 9
#18500000
1!
1&
1/
12
15
#18510000
b0000 1
b00000000 4
#18550000
b00000000 %
b00000000 *
b00000000 :
#19000000
0!
b0111 $
0&
b0111 )
0/
02
05
b0111 9
#19500000
1!
1&
1/
12
15
#19510000
b0000 1
b00000000 4
#19550000
b00000000 *
b00000000 :
#20000000
0!
b1000 $
0&
b1000 )
0/
02
05
b1000 9
#20500000
1!
1&
1/
12
15
#20510000
b0000 1
b00000000 4
#20550000
b00000000 *
b00000000 :
#21000000
0!
b1001 $
0&
b1001 )
0/
02
05
b1001 9
#21500000
1!
1&
1/
12
15
#21510000
b0000 1
b00000000 4
#21550000
b00000000 *
b00000000 :
#22000000
0!
b1010 $
0&
b1010 )
0/
02
05
b1010 9
#22500000
1!
1&
1/
12
15
#22510000
b0000 1
b00000000 4
#22550000
b01100100 %
b01100100 *
b01100100 :
#23000000
0!
b1011 $
0&
b1011 )
0/
02
05
b1011 9
#23500000
1!
1&
1/
12
15
#23510000
b0000 1
b00000000 4
#23550000
b00000000 %
b00000000 *
b00000000 :
#24000000
0!
b1100 $
0&
b1100 )
0/
02
05
b1100 9
#24500000
1!
1&
1/
12
15
#24510000
b0000 1
b00000000 4
#24550000
b00000000 *
b00000000 :
#25000000
0!
b1101 $
0&
b1101 )
0/
02
05
b1101 9
#25500000
1!
1&
1/
12
15
#25510000
b0000 1
b00000000 4
#25550000
b00000000 *
b00000000 :
#26000000
0!
b1110 $
0&
b1110 )
0/
02
05
b1110 9
#26500000
1!
1&
1/
12
15
#26510000
b0000 1
b00000000 4
#26550000
b00000000 *
b00000000 :
#27000000
0!
b1111 $
0&
b1111 )
0/
02
05
b1111 9
#27500000
1!
1&
1/
12
15
#27510000
b0000 1
b00000000 4
#27550000
b00000011 %
b00000011 *
b00000011 :
#28000000
0!
0&
0/
02
05
#28500000
1!
1&
1/
12
15
#28510000
b0000 1
b00000000 4
#28550000
b00000011 *
b00000011 :
