shifter/my_shifter.vhd
-- filepath: /home/weza/Documents/UA/Year-1/S-1/AAD/AAD10-project2/shifter/my_shifter.vhd
library IEEE;
use IEEE.std_logic_1164.all;
use IEEE.numeric_std.all;

entity my_shifter is
    generic (
        DATA_BITS : integer := 8  -- Data DATA_BITS
    );
    port (
        data_in  : in  std_logic_vector(DATA_BITS-1 downto 0);
        sel    : in  std_logic_vector(2 downto 0);  -- Max 8-bit sel
        data_out : out std_logic_vector(DATA_BITS-1 downto 0)
    );
end my_shifter;

architecture behavioral of my_shifter is
    signal stage1, stage2, stage3 : std_logic_vector(DATA_BITS-1 downto 0);
begin
    -- Stage 1: 1-bit sel
    stage1 <= data_in(DATA_BITS-2 downto 0) & '0' when sel(0) = '1' else data_in;
    
    -- Stage 2: 2-bit sel
    stage2 <= stage1(DATA_BITS-3 downto 0) & "00" when sel(1) = '1' else stage1;
    
    -- Stage 3: 4-bit sel
    stage3 <= stage2(DATA_BITS-5 downto 0) & "0000" when sel(2) = '1' else stage2;
    
    -- Output assignment
    data_out <= stage3;
end behavioral;

shifter/shifter_tb.vhd
library IEEE;
use IEEE.std_logic_1164.all;

entity shifter_tb is
end shifter_tb;

architecture stimulus of shifter_tb is
    constant DATA_BITS: integer := 8;  -- Increased to test larger shifts
    -- constant SHIFT_AMOUNT: integer := 3;  -- Test 3-bit shift capability
    signal s_data_in : std_logic_vector(DATA_BITS-1 downto 0);
    signal s_data_out : std_logic_vector(DATA_BITS-1 downto 0);
    signal s_sel : std_logic_vector(2 downto 0);  -- Changed to 3 bits for shift control
begin
    uut : entity work.my_shifter(behavioral)
                generic map (
                    DATA_BITS    => DATA_BITS
                    -- SHIFT_AMOUNT => SHIFT_AMOUNT
                )
                port map (
                    data_in  => s_data_in,
                    data_out => s_data_out,
                    sel      => s_sel
                );

    -- Test different input patterns
    data_in : process
    begin
        -- Test pattern 1: single bit
        s_data_in <= "00000001";
        wait for 100 ps;
        
        -- Test pattern 2: alternating bits
        s_data_in <= "10101010";
        wait for 100 ps;
        
        -- Test pattern 3: all ones
        s_data_in <= "11111111";
        wait for 100 ps;
        
        -- Test pattern 4: random pattern
        s_data_in <= "10110011";
        wait for 100 ps;
        
        wait;
    end process;

    -- Test different shift amounts
    sel : process
    begin
        -- No shift
        s_sel <= "000";
        wait for 25 ps;
        
        -- 1-bit shift
        s_sel <= "001";
        wait for 25 ps;
        
        -- 2-bit shift
        s_sel <= "010";
        wait for 25 ps;
        
        -- 3-bit shift
        s_sel <= "011";
        wait for 25 ps;
        
        -- 4-bit shift
        s_sel <= "100";
        wait for 25 ps;
        
        -- Maximum shift
        s_sel <= "111";
        wait for 25 ps;
        
        wait;
    end process;
end stimulus;

shifter/test_my_shifter.vcd
$date
  Thu Dec 26 10:15:19 2024
$end
$version
  GHDL v0
$end
$timescale
  1 fs
$end
$scope module standard $end
$upscope $end
$scope module textio $end
$upscope $end
$scope module std_logic_1164 $end
$upscope $end
$scope module numeric_std $end
$upscope $end
$scope module shifter_tb $end
$var reg 8 ! s_data_in[7:0] $end
$var reg 8 " s_data_out[7:0] $end
$var reg 3 # s_sel[2:0] $end
$scope module uut $end
$var reg 8 $ data_in[7:0] $end
$var reg 3 % sel[2:0] $end
$var reg 8 & data_out[7:0] $end
$var reg 8 ' stage1[7:0] $end
$var reg 8 ( stage2[7:0] $end
$var reg 8 ) stage3[7:0] $end
$upscope $end
$upscope $end
$enddefinitions $end
#0
b00000001 !
b00000001 "
b000 #
b00000001 $
b000 %
b00000001 &
b00000001 '
b00000001 (
b00000001 )
#25000
b00000010 "
b001 #
b001 %
b00000010 &
b00000010 '
b00000010 (
b00000010 )
#50000
b00000100 "
b010 #
b010 %
b00000100 &
b00000001 '
b00000100 (
b00000100 )
#75000
b00001000 "
b011 #
b011 %
b00001000 &
b00000010 '
b00001000 (
b00001000 )
#100000
b10101010 !
b10100000 "
b100 #
b10101010 $
b100 %
b10100000 &
b10101010 '
b10101010 (
b10100000 )
#125000
b00000000 "
b111 #
b111 %
b00000000 &
b01010100 '
b01010000 (
b00000000 )
#150000
#200000
b11111111 !
b10000000 "
b11111111 $
b10000000 &
b11111110 '
b11111000 (
b10000000 )
#300000
b10110011 !
b10110011 $
b01100110 '
b10011000 (
